matcha_ml/VERSION
matcha_ml/__init__.py
matcha_ml/cli/__init__.py
matcha_ml/cli/_validation.py
matcha_ml/cli/cli.py
matcha_ml/cli/constants.py
matcha_ml/cli/destroy.py
matcha_ml/cli/ui/emojis.py
matcha_ml/cli/ui/print_messages.py
matcha_ml/cli/ui/resource_message_builders.py
matcha_ml/cli/ui/spinner.py
matcha_ml/cli/ui/status_message_builders.py
matcha_ml/cli/ui/user_approval_functions.py
matcha_ml/config/__init__.py
matcha_ml/config/matcha_config.py
matcha_ml/constants.py
matcha_ml/core/__init__.py
matcha_ml/core/_validation.py
matcha_ml/core/core.py
matcha_ml/errors.py
matcha_ml/infrastructure/default/.gitignore
matcha_ml/infrastructure/default/.terraform.lock.hcl
matcha_ml/infrastructure/default/README.md
matcha_ml/infrastructure/default/aks/README.md
matcha_ml/infrastructure/default/aks/main.tf
matcha_ml/infrastructure/default/aks/output.tf
matcha_ml/infrastructure/default/aks/variables.tf
matcha_ml/infrastructure/default/azure_container_registry/README.md
matcha_ml/infrastructure/default/azure_container_registry/main.tf
matcha_ml/infrastructure/default/azure_container_registry/output.tf
matcha_ml/infrastructure/default/azure_container_registry/variables.tf
matcha_ml/infrastructure/default/configure_kubectl.tf
matcha_ml/infrastructure/default/data_version_control_storage/README.md
matcha_ml/infrastructure/default/data_version_control_storage/main.tf
matcha_ml/infrastructure/default/data_version_control_storage/output.tf
matcha_ml/infrastructure/default/data_version_control_storage/providers.tf
matcha_ml/infrastructure/default/data_version_control_storage/variables.tf
matcha_ml/infrastructure/default/helm.tf
matcha_ml/infrastructure/default/kubernetes.tf
matcha_ml/infrastructure/default/main.tf
matcha_ml/infrastructure/default/mlflow_module/README.md
matcha_ml/infrastructure/default/mlflow_module/getURI.tf
matcha_ml/infrastructure/default/mlflow_module/main.tf
matcha_ml/infrastructure/default/mlflow_module/output.tf
matcha_ml-0.3.0.dist-info/LICENSE
matcha_ml-0.3.0.dist-info/METADATA
matcha_ml-0.3.0.dist-info/WHEEL
matcha_ml-0.3.0.dist-info/entry_points.txt
matcha_ml-0.3.0.dist-info/RECORD
