Metadata-Version: 2.3
Name: matcha-ml
Version: 0.3.0
Summary: Matcha: An open source tool for provisioning MLOps environments to the cloud.
License: Apache-2.0
Keywords: production,mlops,devops,machine learning
Author: FuzzyLabs
Author-email: info@fuzzylabs.ai
Requires-Python: >=3.8,<4.0
Classifier: Development Status :: 3 - Alpha
Classifier: Intended Audience :: Science/Research
Classifier: License :: OSI Approved :: Apache Software License
Classifier: Programming Language :: Python :: 3
Classifier: Programming Language :: Python :: 3.8
Classifier: Programming Language :: Python :: 3.9
Classifier: Programming Language :: Python :: 3.10
Classifier: Programming Language :: Python :: 3.11
Classifier: Programming Language :: Python :: 3.12
Classifier: Programming Language :: Python :: 3.13
Classifier: Programming Language :: Python :: Implementation
Classifier: Topic :: Software Development
Classifier: Topic :: Software Development :: Libraries :: Python Modules
Requires-Dist: azure-identity (>=1.12.0,<2.0.0)
Requires-Dist: azure-mgmt-authorization (>=3.0.0,<4.0.0)
Requires-Dist: azure-mgmt-confluent (>=1.0.0,<2.0.0)
Requires-Dist: azure-mgmt-resource (>=23.0.0,<24.0.0)
Requires-Dist: azure-mgmt-storage (>=21.0.0,<22.0.0)
Requires-Dist: azure-mgmt-subscription (>=3.1.1,<4.0.0)
Requires-Dist: azure-storage-blob (>=12.16.0,<13.0.0)
Requires-Dist: dataclasses-json (>=0.5.7,<0.6.0)
Requires-Dist: python-terraform (>=0.10.1,<0.11.0)
Requires-Dist: pyyaml (>=6.0.1,<7.0.0)
Requires-Dist: requests (>=2.31.0,<3.0.0)
Requires-Dist: segment-analytics-python (>=2.2.2,<3.0.0)
Requires-Dist: typer[all] (>=0.7.0,<0.8.0)
Requires-Dist: types-pyyaml (>=6.0.12.9,<7.0.0.0)
Requires-Dist: types-urllib3 (>=1.26.25.13,<2.0.0.0)
Requires-Dist: urllib3 (==1.26.6)
Project-URL: Bug Tracker, https://github.com/fuzzylabs/matcha/issues
Project-URL: Documentation, http://fuzzylabs.github.io/matcha
Project-URL: Homepage, http://fuzzylabs.github.io/matcha
Project-URL: Repository, https://github.com/fuzzylabs/matcha
